lazycph/__init__.py
lazycph/__main__.py
lazycph/app.py
lazycph/engines.py
lazycph/workspace.py
lazycph/screens/__init__.py
lazycph/screens/companion.py
lazycph/screens/file_picker.py
lazycph/widgets/__init__.py
lazycph/widgets/editor.py
lazycph/widgets/testcase_item.py
lazycph/widgets/testcase_list.py
lazycph-1.2.2.dist-info/METADATA
lazycph-1.2.2.dist-info/WHEEL
lazycph-1.2.2.dist-info/entry_points.txt
lazycph-1.2.2.dist-info/licenses/LICENSE
lazycph-1.2.2.dist-info/RECORD
