Metadata-Version: 2.4
Name: lazycph
Version: 1.2.2
Summary: Competitive Programming Helper
Project-URL: Homepage, https://github.com/TheComputerM/lazycph
Project-URL: Repository, https://github.com/TheComputerM/lazycph.git
Project-URL: Issues, https://github.com/TheComputerM/lazycph/issues
License-Expression: MIT
License-File: LICENSE
Keywords: competitive-programming,textual,tui
Classifier: Environment :: Console
Classifier: Intended Audience :: Education
Classifier: Natural Language :: English
Classifier: Topic :: Terminals
Requires-Python: >=3.13
Requires-Dist: textual>=6.6.0
